backuppurge/__init__.py
backuppurge/test_backuppurge.py
backuppurge-1.0.7.data/data/share/man/man1/backuppurge.1
backuppurge-1.0.7.data/scripts/backuppurge
backuppurge-1.0.7.dist-info/LICENSE
backuppurge-1.0.7.dist-info/METADATA
backuppurge-1.0.7.dist-info/WHEEL
backuppurge-1.0.7.dist-info/top_level.txt
backuppurge-1.0.7.dist-info/RECORD
