Metadata-Version: 2.2
Name: backuppurge
Version: 1.0.7
Summary: Selectively purge daily full backups
Home-page: https://thp.io/2013/backuppurge/
Download-URL: https://thp.io/2013/backuppurge/backuppurge-1.0.7.tar.gz
Author: Thomas Perl
Author-email: m@thp.io
License: Simplified BSD License
License-File: LICENSE
Dynamic: author
Dynamic: author-email
Dynamic: description
Dynamic: description-content-type
Dynamic: download-url
Dynamic: home-page
Dynamic: license
Dynamic: summary
